MANIFEST.in
README.txt
setup.cfg
setup.py
docs/HISTORY.txt
docs/INSTALL.txt
docs/LICENSE.GPL
docs/LICENSE.txt
ityou/__init__.py
ityou.extuserprofile.egg-info/PKG-INFO
ityou.extuserprofile.egg-info/SOURCES.txt
ityou.extuserprofile.egg-info/dependency_links.txt
ityou.extuserprofile.egg-info/entry_points.txt
ityou.extuserprofile.egg-info/namespace_packages.txt
ityou.extuserprofile.egg-info/not-zip-safe
ityou.extuserprofile.egg-info/paster_plugins.txt
ityou.extuserprofile.egg-info/requires.txt
ityou.extuserprofile.egg-info/top_level.txt
ityou/extuserprofile/__init__.py
ityou/extuserprofile/config.py
ityou/extuserprofile/configure.zcml
ityou/extuserprofile/dbapi.py
ityou/extuserprofile/interfaces.py
ityou/extuserprofile/monkeypatches.py
ityou/extuserprofile/skins.zcml
ityou/extuserprofile/tests.py
ityou/extuserprofile/translate.sh
ityou/extuserprofile/userschema.py
ityou/extuserprofile/utils.py
ityou/extuserprofile/Extensions/Install.py
ityou/extuserprofile/Extensions/__init__.py
ityou/extuserprofile/browser/__init__.py
ityou/extuserprofile/browser/configure.zcml
ityou/extuserprofile/browser/controlpanel.py
ityou/extuserprofile/browser/controlpanel.py~
ityou/extuserprofile/browser/crop_portrait.py
ityou/extuserprofile/browser/personal_images.py
ityou/extuserprofile/browser/user_export.py
ityou/extuserprofile/browser/user_import.py
ityou/extuserprofile/browser/userprofile.py
ityou/extuserprofile/browser/users.py
ityou/extuserprofile/browser/images/back_disabled.jpg
ityou/extuserprofile/browser/images/back_disabled.png
ityou/extuserprofile/browser/images/back_enabled.jpg
ityou/extuserprofile/browser/images/back_enabled.png
ityou/extuserprofile/browser/images/edit-icon-active.png
ityou/extuserprofile/browser/images/edit-icon.png
ityou/extuserprofile/browser/images/email.png
ityou/extuserprofile/browser/images/facebook.png
ityou/extuserprofile/browser/images/forward_disabled.jpg
ityou/extuserprofile/browser/images/forward_disabled.png
ityou/extuserprofile/browser/images/forward_enabled.jpg
ityou/extuserprofile/browser/images/forward_enabled.png
ityou/extuserprofile/browser/images/icq.png
ityou/extuserprofile/browser/images/ityou-esi-extuserprofile-icon.png
ityou/extuserprofile/browser/images/linkedin.png
ityou/extuserprofile/browser/images/skype.png
ityou/extuserprofile/browser/images/sort_asc.png
ityou/extuserprofile/browser/images/sort_asc_disabled.png
