Metadata-Version: 1.1
Name: ityou.extuserprofile
Version: 1.3.1
Summary: Extended User Profile
Home-page: http://www.ityou.de/esi/
Author: ITYOU/LM
Author-email: lm@ityou.de
License: GPL
Keywords: Social Intranet,Plone,user profiles
Platform: UNKNOWN
Classifier: Framework :: Plone
Classifier: Programming Language :: Python
